faasmsctl/__init__.py
faasmsctl/main.py
faasmsctl/bin/gen_proto_files.py
faasmsctl/tasks/__init__.py
faasmsctl/tasks/cli.py
faasmsctl/tasks/delete.py
faasmsctl/tasks/deploy.py
faasmsctl/tasks/flush.py
faasmsctl/tasks/generate.py
faasmsctl/tasks/invoke.py
faasmsctl/tasks/logs.py
faasmsctl/tasks/monitor.py
faasmsctl/tasks/restart.py
faasmsctl/tasks/status.py
faasmsctl/tasks/upload.py
faasmsctl/util/backend.py
faasmsctl/util/batch.py
faasmsctl/util/compose.py
faasmsctl/util/config.py
faasmsctl/util/deploy.py
faasmsctl/util/docker.py
faasmsctl/util/env.py
faasmsctl/util/faasm.py
faasmsctl/util/flush.py
faasmsctl/util/invoke.py
faasmsctl/util/k8s.py
faasmsctl/util/message.py
faasmsctl/util/network.py
faasmsctl/util/planner.py
faasmsctl/util/random.py
faasmsctl/util/results.py
faasmsctl/util/upload.py
faasmsctl/util/version.py
faasmsctl-0.0.4.dist-info/LICENSE.md
faasmsctl-0.0.4.dist-info/METADATA
faasmsctl-0.0.4.dist-info/WHEEL
faasmsctl-0.0.4.dist-info/entry_points.txt
faasmsctl-0.0.4.dist-info/top_level.txt
faasmsctl-0.0.4.dist-info/RECORD
