Metadata-Version: 2.1
Name: faasmsctl
Version: 0.0.4
Summary: Command line tool to deploy, manage, and interact with Faasm Stream
Author-email: Faasm Team <foo@bar.com>, Tianyu <foo@bar.com>
Project-URL: Homepage, https://github.com/faasm/faasmctl
Project-URL: Bug Tracker, https://github.com/faasm/faasmctl/issues
Classifier: Programming Language :: Python :: 3
Classifier: Operating System :: OS Independent
Requires-Python: >=3.7
License-File: LICENSE.md
Requires-Dist: invoke ==2.1.3
Requires-Dist: requests ==2.31.0
Requires-Dist: protobuf ==4.23.4
